servify/__init__.py
servify/commons.py
servify/helpers.py
servify/logging.py
servify/paths.py
servify/servify_configs.py
servify/settings.py
servify/shared_commons.py
servify/spark_logging.py
servify/tests/__init__.py
servify/tests/conftest.py
servify/tests/test_commons.py
servify-0.0.25.dist-info/licenses/LICENCE
servify-0.0.25.dist-info/METADATA
servify-0.0.25.dist-info/WHEEL
servify-0.0.25.dist-info/top_level.txt
servify-0.0.25.dist-info/RECORD
