Metadata-Version: 2.4
Name: servify
Version: 0.0.25
Summary: A Python library that simplifies data manipulation and workflow development with PySpark in Databricks environments.
Author: Felipe Pegoraro
Author-email: felipepegoraro93@gmail.com
License: MIT
Keywords: databricks spark pyspark
License-File: LICENCE
Requires-Dist: pyspark>=4.0.0
Requires-Dist: delta-spark>=4.0.1
Requires-Dist: loguru>=0.7.3
Requires-Dist: holidays>=0.88
Requires-Dist: pandas>=2.3.2
Requires-Dist: pyarrow>=21.0.0
Requires-Dist: tqdm>=4.67.1
Requires-Dist: openpyxl>=3.1.2
Dynamic: author
Dynamic: author-email
Dynamic: description
Dynamic: description-content-type
Dynamic: keywords
Dynamic: license
Dynamic: license-file
Dynamic: requires-dist
Dynamic: summary
